robinhood_mcp/__init__.py
robinhood_mcp/auth.py
robinhood_mcp/server.py
robinhood_mcp/tools.py
robinhood_mcp-0.1.0.dist-info/licenses/LICENSE
robinhood_mcp-0.1.0.dist-info/METADATA
robinhood_mcp-0.1.0.dist-info/WHEEL
robinhood_mcp-0.1.0.dist-info/entry_points.txt
robinhood_mcp-0.1.0.dist-info/top_level.txt
robinhood_mcp-0.1.0.dist-info/RECORD
