Metadata-Version: 2.4
Name: robinhood-mcp
Version: 0.1.0
Summary: Read-only MCP server for Robinhood portfolio research
Author-email: Jack Arturo <jack@verygoodplugins.com>
License: MIT
Project-URL: Homepage, https://verygoodplugins.com/?utm_source=github
Project-URL: Repository, https://github.com/verygoodplugins/robinhood-mcp
Classifier: Development Status :: 3 - Alpha
Classifier: License :: OSI Approved :: MIT License
Classifier: Programming Language :: Python :: 3.11
Classifier: Programming Language :: Python :: 3.12
Requires-Python: >=3.11
License-File: LICENSE
Requires-Dist: fastmcp>=0.4.0
Requires-Dist: robin_stocks>=3.0.0
Requires-Dist: python-dotenv>=1.0.0
Requires-Dist: pyotp>=2.9.0
Provides-Extra: dev
Requires-Dist: pytest>=7.0.0; extra == "dev"
Requires-Dist: pytest-asyncio>=0.21.0; extra == "dev"
Requires-Dist: pytest-cov>=4.0.0; extra == "dev"
Requires-Dist: ruff>=0.1.0; extra == "dev"
Dynamic: license-file
